MANIFEST.in
PKG-INFO
README.txt
setup.cfg
setup.py
dist/medialog.tinymceplugins.helpmenu-0.2.7.zip
docs/HISTORY.txt
docs/INSTALL.txt
docs/LICENSE.GPL
docs/LICENSE.txt
medialog/.DS_Store
medialog/__init__.py
medialog.tinymceplugins.helpmenu.egg-info/PKG-INFO
medialog.tinymceplugins.helpmenu.egg-info/SOURCES.txt
medialog.tinymceplugins.helpmenu.egg-info/dependency_links.txt
medialog.tinymceplugins.helpmenu.egg-info/entry_points.txt
medialog.tinymceplugins.helpmenu.egg-info/namespace_packages.txt
medialog.tinymceplugins.helpmenu.egg-info/not-zip-safe
medialog.tinymceplugins.helpmenu.egg-info/requires.txt
medialog.tinymceplugins.helpmenu.egg-info/top_level.txt
medialog/tinymceplugins/.DS_Store
medialog/tinymceplugins/__init__.py
medialog/tinymceplugins/helpmenu/.DS_Store
medialog/tinymceplugins/helpmenu/__init__.py
medialog/tinymceplugins/helpmenu/configure.zcml
medialog/tinymceplugins/helpmenu/tests.py
medialog/tinymceplugins/helpmenu/locales/.DS_Store
medialog/tinymceplugins/helpmenu/locales/medialog.tinymceplugins.helpmenu.pot
medialog/tinymceplugins/helpmenu/locales/de/LC_MESSAGES/medialog.tinymceplugins.helpmenu.po
medialog/tinymceplugins/helpmenu/locales/en/LC_MESSAGES/medialog.tinymceplugins.helpmenu.po
medialog/tinymceplugins/helpmenu/locales/no/.DS_Store
medialog/tinymceplugins/helpmenu/locales/no/LC_MESSAGES/medialog.tinymceplugins.helpmenu.po
medialog/tinymceplugins/helpmenu/profiles/.DS_Store
medialog/tinymceplugins/helpmenu/profiles/default/actions.xml
medialog/tinymceplugins/helpmenu/profiles/default/metadata.xml
medialog/tinymceplugins/helpmenu/profiles/default/skins.xml
medialog/tinymceplugins/helpmenu/profiles/default/tinymce.xml
medialog/tinymceplugins/helpmenu/skins/.DS_Store
medialog/tinymceplugins/helpmenu/skins/tinymce_plugin_helpmenu/.DS_Store
medialog/tinymceplugins/helpmenu/skins/tinymce_plugin_helpmenu/00.htm
medialog/tinymceplugins/helpmenu/skins/tinymce_plugin_helpmenu/01.htm
medialog/tinymceplugins/helpmenu/skins/tinymce_plugin_helpmenu/02.htm
medialog/tinymceplugins/helpmenu/skins/tinymce_plugin_helpmenu/03.htm
medialog/tinymceplugins/helpmenu/skins/tinymce_plugin_helpmenu/04.htm
medialog/tinymceplugins/helpmenu/skins/tinymce_plugin_helpmenu/05.htm
medialog/tinymceplugins/helpmenu/skins/tinymce_plugin_helpmenu/06.html
medialog/tinymceplugins/helpmenu/skins/tinymce_plugin_helpmenu/07.htm
medialog/tinymceplugins/helpmenu/skins/tinymce_plugin_helpmenu/08.htm
