Metadata-Version: 1.0
Name: medialog.tinymceplugins.helpmenu
Version: 0.2.8
Summary: Add on that displays help (how-tos) inside TinyMCE
Home-page: http://svn.plone.org/svn/collective/medialog.tinymceplugins.helpmenu/
Author: Espen Moe-Nilssen
Author-email: espen@medialog.no
License: GPL
Keywords: tinymce plugin help menu
Platform: UNKNOWN
Classifier: Development Status :: 3 - Alpha
Classifier: Framework :: Plone
Classifier: Programming Language :: Python
Classifier: Programming Language :: JavaScript
